bunnycdn/__init__.py
bunnycdn/abuse_case.py
bunnycdn/billing.py
bunnycdn/dmca.py
bunnycdn/dns_zones.py
bunnycdn/errors.py
bunnycdn/files.py
bunnycdn/logging.py
bunnycdn/pull_zones.py
bunnycdn/purge.py
bunnycdn/statistics.py
bunnycdn/storage_zones.py
bunnycdn/support.py
bunnycdn/users.py
bunnycdn/utils.py
bunnycdn/video_library.py
bunnycdn-0.0.3.dist-info/WHEEL
bunnycdn-0.0.3.dist-info/METADATA
bunnycdn-0.0.3.dist-info/RECORD
