Metadata-Version: 2.1
Name: bunnycdn
Version: 0.0.3
Summary: An Unofficial SDK for BunnyCDN
Author: Dan Sikes
Author-email: dansikes7@gmail.com
Requires-Python: >=3.10,<4.0
Classifier: Programming Language :: Python :: 3
Classifier: Programming Language :: Python :: 3.10
Requires-Dist: requests (>=2.28.1,<3.0.0)
